README.md
setup.cfg
setup.py
ultimateEda/__init__.py
ultimateEda/report.py
ultimateEda.egg-info/PKG-INFO
ultimateEda.egg-info/SOURCES.txt
ultimateEda.egg-info/dependency_links.txt
ultimateEda.egg-info/not-zip-safe
ultimateEda.egg-info/top_level.txt