Metadata-Version: 2.1
Name: ultimateEda
Version: 0.0.3
Summary: EDA & Univariate Analysis
Home-page: UNKNOWN
Author-email: ranjitmaity95@gmail.com
License: UNKNOWN
Platform: UNKNOWN
